pyppet_models/__init__.py
pyppet_models/franka_research_3/model.py
pyppet_models/franka_research_3/urdf_franka.py
pyppet_models/franka_research_3/visualize_franka.py
pyppet_models/franka_research_3/assets/finger.glb
pyppet_models/franka_research_3/assets/hand.glb
pyppet_models/franka_research_3/assets/link0.glb
pyppet_models/franka_research_3/assets/link1.glb
pyppet_models/franka_research_3/assets/link2.glb
pyppet_models/franka_research_3/assets/link3.glb
pyppet_models/franka_research_3/assets/link4.glb
pyppet_models/franka_research_3/assets/link5.glb
pyppet_models/franka_research_3/assets/link6.glb
pyppet_models/franka_research_3/assets/link7.glb
pyppet_models-1.1.1.dist-info/METADATA
pyppet_models-1.1.1.dist-info/WHEEL
pyppet_models-1.1.1.dist-info/licenses/LICENSE
pyppet_models-1.1.1.dist-info/RECORD
