Metadata-Version: 2.4
Name: pyppet_models
Version: 1.1.1
Summary: pyppet_models contains examples for using pyppet: https://github.com/david-dorf/pyppet
License: MIT
License-File: LICENSE
Requires-Python: <3.13,>=3.10
Requires-Dist: pyppet[viz]==1.0.2
